CHANGELOG
CONTRIBUTORS
LICENSE
MANIFEST.in
README.rst
requirements.txt
setup.py
updiancmd
UPDIAN.egg-info/PKG-INFO
UPDIAN.egg-info/SOURCES.txt
UPDIAN.egg-info/dependency_links.txt
UPDIAN.egg-info/not-zip-safe
UPDIAN.egg-info/requires.txt
UPDIAN.egg-info/top_level.txt
updian/__init__.py
updian/config.py
updian/fabfile.py
updian/fabric_utils.py
updian/passwd.py
updian/serverlist.py
updian/cmd/__init__.py
updian/cmd/convert_serverlist.py
updian/cmd/runserver.py
updian/cron/__init__.py
updian/cron/collect.py
updian/cron/update.py
updian/frontend/__init__.py
updian/frontend/basicauth.py
updian/frontend/forms.py
updian/frontend/utils.py
updian/frontend/validation.py
updian/frontend/views.py
updian/frontend/static/logo.png
updian/frontend/static/style.css
updian/frontend/static/js/.gitignore
updian/frontend/templates/base.html
updian/frontend/templates/critical_error.html
updian/frontend/templates/index.html
updian/frontend/templates/logs_list.html
updian/frontend/templates/queue_show.html
updian/frontend/templates/server_edit.html
updian/frontend/templates/server_list.html