Metadata-Version: 1.0
Name: UPDIAN
Version: 0.6
Summary: A program for monitoring and executing updates on remote systems
Home-page: http://www.robhost.de/updian/
Author: Dirk Dankhoff
Author-email: dd@robhost.de
License: GPLv2+ <http://www.gnu.org/licenses/gpl-2.0.en.html>
Platform: UNKNOWN
Classifier: Development Status :: 4 - Beta
Classifier: Intended Audience :: System Administrators
Classifier: Natural Language :: English
Classifier: Operating System :: POSIX :: Linux
Classifier: Topic :: System :: Monitoring
Classifier: Topic :: System :: Systems Administration
